powerxrd/__init__.py
powerxrd/chart.py
powerxrd/data.py
powerxrd/model.py
powerxrd/refine.py
powerxrd/utilities.py
powerxrd/workflow.py
powerxrd-3.0.0.dist-info/LICENSE
powerxrd-3.0.0.dist-info/METADATA
powerxrd-3.0.0.dist-info/WHEEL
powerxrd-3.0.0.dist-info/RECORD
