Metadata-Version: 2.3
Name: powerxrd
Version: 3.0.0
Summary: Python tools for powder XRD data analysis – now with Rietveld refinement support.
License: MIT
Keywords: XRD,Rietveld,materials science,diffraction,crystallography
Author: andrewrgarcia
Author-email: garcia.gtr@gmail.com
Requires-Python: >=3.9,<3.13
Classifier: License :: OSI Approved :: MIT License
Classifier: Programming Language :: Python :: 3
Classifier: Programming Language :: Python :: 3.9
Classifier: Programming Language :: Python :: 3.10
Classifier: Programming Language :: Python :: 3.11
Classifier: Programming Language :: Python :: 3.12
Requires-Dist: matplotlib (>=3.7.0,<4.0.0)
Requires-Dist: numpy (>=1.26,<2.0)
Requires-Dist: pandas (>=2.2.2,<3.0.0)
Requires-Dist: scipy (>=1.10.0,<2.0.0)
Project-URL: Homepage, https://github.com/andrewrgarcia/powerxrd
Project-URL: Repository, https://github.com/andrewrgarcia/powerxrd
